devvio_inn_util/__init__.py
devvio_inn_util/lib_const.py
devvio_inn_util/lib_creds.py
inn_util/__init__.py
inn_util/lib_const.py
inn_util/lib_creds.py
devvio_inn_util-0.3.dist-info/METADATA
devvio_inn_util-0.3.dist-info/WHEEL
devvio_inn_util-0.3.dist-info/top_level.txt
devvio_inn_util-0.3.dist-info/RECORD
