Metadata-Version: 2.1
Name: devvio-inn-util
Version: 0.3
Summary: Utility to be used inside Devvio projects
Home-page: UNKNOWN
Author: Mateus Sens
Author-email: mateus.sens@tarmac.io
License: Devvio
Platform: UNKNOWN
